[
  {
    "scientificNames": [""],
    "commonNames": [""],
    "type": "Shrub",
    "lightNeeds": ,
    "waterNeeds": ,
    "flowerColors": [""],
    "wildlifeSupport": [],
    "foodUses": [""],
    "otherUses": [""],
    "images": {
      "small": "",
      "original": ""
    },
    "toxic": "No",
    "spreadsVigorously": "Yes",
    "otherWarnings": [""],
    "evergreen": "Yes",
    "propagationNeeds": "Stratification"
  },
  {
    "scientificNames": [""],
    "commonNames": [""],
    "type": "Shrub",
    "lightNeeds": ,
    "waterNeeds": ,
    "flowerColors": [""],
    "wildlifeSupport": [],
    "foodUses": [""],
    "otherUses": [""],
    "images": {
      "small": "",
      "original": ""
    },
    "toxic": "No",
    "spreadsVigorously": "Yes",
    "otherWarnings": [""],
    "evergreen": "Yes",
    "propagationNeeds": "Stratification"
  },
  {
    "scientificNames": [""],
    "commonNames": [""],
    "type": "Shrub",
    "lightNeeds": ,
    "waterNeeds": ,
    "flowerColors": [""],
    "wildlifeSupport": [],
    "foodUses": [""],
    "otherUses": [""],
    "images": {
      "small": "",
      "original": ""
    },
    "toxic": "No",
    "spreadsVigorously": "Yes",
    "otherWarnings": [""],
    "evergreen": "Yes",
    "propagationNeeds": "Stratification"
  },
  {
    "scientificNames": [""],
    "commonNames": [""],
    "type": "Shrub",
    "lightNeeds": ,
    "waterNeeds": ,
    "flowerColors": [""],
    "wildlifeSupport": [],
    "foodUses": [""],
    "otherUses": [""],
    "images": {
      "small": "",
      "original": ""
    },
    "toxic": "No",
    "spreadsVigorously": "Yes",
    "otherWarnings": [""],
    "evergreen": "Yes",
    "propagationNeeds": "Stratification"
  },
]